README.md
setup.py
oatomobile/__init__.py
oatomobile/_metadata.py
oatomobile.egg-info/PKG-INFO
oatomobile.egg-info/SOURCES.txt
oatomobile.egg-info/dependency_links.txt
oatomobile.egg-info/requires.txt
oatomobile.egg-info/top_level.txt
oatomobile/baselines/__init__.py
oatomobile/baselines/base.py
oatomobile/baselines/rulebased/__init__.py
oatomobile/baselines/rulebased/autopilot/__init__.py
oatomobile/baselines/rulebased/autopilot/agent.py
oatomobile/baselines/rulebased/autopilot/run.py
oatomobile/baselines/rulebased/blind/__init__.py
oatomobile/baselines/rulebased/blind/agent.py
oatomobile/baselines/rulebased/blind/run.py
oatomobile/baselines/tf/__init__.py
oatomobile/baselines/tf/logging.py
oatomobile/baselines/tf/typing.py
oatomobile/baselines/torch/__init__.py
oatomobile/baselines/torch/logging.py
oatomobile/baselines/torch/models.py
oatomobile/baselines/torch/transforms.py
oatomobile/baselines/torch/typing.py
oatomobile/baselines/torch/cil/__init__.py
oatomobile/baselines/torch/cil/agent.py
oatomobile/baselines/torch/cil/model.py
oatomobile/baselines/torch/cil/train.py
oatomobile/baselines/torch/dim/__init__.py
oatomobile/baselines/torch/dim/agent.py
oatomobile/baselines/torch/dim/model.py
oatomobile/baselines/torch/dim/train.py
oatomobile/baselines/torch/rip/__init__.py
oatomobile/baselines/torch/rip/agent.py
oatomobile/benchmarks/__init__.py
oatomobile/benchmarks/carnovel/__init__.py
oatomobile/benchmarks/carnovel/benchmark.py
oatomobile/benchmarks/corl2017/__init__.py
oatomobile/benchmarks/corl2017/benchmark.py
oatomobile/core/__init__.py
oatomobile/core/agent.py
oatomobile/core/benchmark.py
oatomobile/core/dataset.py
oatomobile/core/loop.py
oatomobile/core/registry.py
oatomobile/core/rl.py
oatomobile/core/simulator.py
oatomobile/core/typing.py
oatomobile/datasets/__init__.py
oatomobile/datasets/carla.py
oatomobile/envs/__init__.py
oatomobile/envs/carla.py
oatomobile/simulators/__init__.py
oatomobile/simulators/carla/__init__.py
oatomobile/simulators/carla/defaults.py
oatomobile/simulators/carla/simulator.py
oatomobile/util/__init__.py
oatomobile/util/carla.py
oatomobile/util/graphics.py
oatomobile/util/uuid.py