Metadata-Version: 2.1
Name: oatomobile
Version: 0.1.0
Summary: The oatomobile is a tool for developing and testing driving agents on the CARLA simulator
Home-page: https://github.com/oatml/oatomobile
Author: Oxford Applied and Theoretical Machine Learning Group
Author-email: oatml@googlegroups.com
License: Apache License, Version 2.0
Platform: UNKNOWN
Classifier: Development Status :: 3 - Alpha
Classifier: Topic :: Software Development :: Build Tools
Classifier: License :: OSI Approved :: Apache Software License
Classifier: Operating System :: POSIX :: Linux
Classifier: Programming Language :: Python :: 3
Classifier: Programming Language :: Python :: 3.5
Classifier: Topic :: Scientific/Engineering :: Artificial Intelligence
Provides-Extra: tf
Provides-Extra: torch
